cqtech_metrics/__init__.py
cqtech_metrics/auth.py
cqtech_metrics/client.py
cqtech_metrics/exceptions.py
cqtech_metrics/types.py
cqtech_metrics/utils.py
cqtech_metrics/models/__init__.py
cqtech_metrics/models/auth.py
cqtech_metrics/models/base.py
cqtech_metrics/models/metrics.py
cqtech_metrics/models/scenes.py
cqtech_metrics-0.1.0.dist-info/licenses/LICENSE
cqtech_metrics-0.1.0.dist-info/METADATA
cqtech_metrics-0.1.0.dist-info/WHEEL
cqtech_metrics-0.1.0.dist-info/top_level.txt
cqtech_metrics-0.1.0.dist-info/RECORD
