Metadata-Version: 2.4
Name: cqtech-metrics
Version: 0.1.0
Summary: A Python SDK for interacting with the CQTech Metrics OpenAPI
Home-page: http://github.com/liudonghua123/cqtech-metrics
Author: CQTech
Author-email: liudonghua <liudonghua123@gmail.com>
License: MIT
Project-URL: Homepage, http://github.com/liudonghua123/cqtech-metrics
Project-URL: Repository, http://github.com/liudonghua123/cqtech-metrics
Project-URL: Bug Reports, http://github.com/liudonghua123/cqtech-metrics/issues
Project-URL: Changelog, https://github.com/liudonghua123/cqtech-metrics/releases
Classifier: Development Status :: 4 - Beta
Classifier: Intended Audience :: Developers
Classifier: License :: OSI Approved :: MIT License
Classifier: Operating System :: OS Independent
Classifier: Programming Language :: Python :: 3
Classifier: Programming Language :: Python :: 3.7
Classifier: Programming Language :: Python :: 3.8
Classifier: Programming Language :: Python :: 3.9
Classifier: Programming Language :: Python :: 3.10
Classifier: Programming Language :: Python :: 3.11
Classifier: Programming Language :: Python :: 3.12
Classifier: Programming Language :: Python :: 3.13
Requires-Python: >=3.7
License-File: LICENSE
Requires-Dist: requests>=2.25.0
Requires-Dist: pydantic>=2.0.0
Requires-Dist: typing-extensions>=4.0.0
Requires-Dist: python-dotenv>=1.0.0
Provides-Extra: dev
Requires-Dist: pytest>=6.0; extra == "dev"
Requires-Dist: pytest-mock; extra == "dev"
Requires-Dist: black; extra == "dev"
Requires-Dist: flake8; extra == "dev"
Dynamic: author
Dynamic: home-page
Dynamic: license-file
Dynamic: requires-python
